smtp_py-0.1.3.dist-info/licenses/LICENSE
smtppy/__init__.py
smtppy/smtppy.py
smtp_py-0.1.3.dist-info/METADATA
smtp_py-0.1.3.dist-info/WHEEL
smtp_py-0.1.3.dist-info/top_level.txt
smtp_py-0.1.3.dist-info/RECORD
